tigrina/__init__.py
tigrina/tg_adjectives.py
tigrina/tg_alphabets.py
tigrina/tg_code_decode.py
tigrina/tg_common.py
tigrina/tg_data_process.py
tigrina/tg_main.py
tigrina/tg_nouns.py
tigrina/tg_test.py
tigrina/tg_verb_to_be.py
tigrina/tg_verbs.py
tigrina/tg_data/adjectives.csv
tigrina/tg_data/adverbs.csv
tigrina/tg_data/nouns.csv
tigrina/tg_data/paired_words.csv
tigrina/tg_data/sentence.csv
tigrina/tg_data/single_words.csv
tigrina/tg_data/tokenized_data.csv
tigrina/tg_data/verbs.csv
tigrina/tg_data/word_families.csv
tigrina-2.0.2.dist-info/LICENSE
tigrina-2.0.2.dist-info/METADATA
tigrina-2.0.2.dist-info/WHEEL
tigrina-2.0.2.dist-info/entry_points.txt
tigrina-2.0.2.dist-info/top_level.txt
tigrina-2.0.2.dist-info/RECORD
