Metadata-Version: 2.1
Name: tigrina
Version: 2.0.2
Summary: Tigrina alphabet processing, which helps to write Tigrina by Tigrina alphabets and other functionalities for manipulation of tigrina words.
Home-page: UNKNOWN
Author: Gide Segid
Author-email: gidesegid@gmail.com
License: MIT
Platform: UNKNOWN
Classifier: Programming Language :: Python :: 3
Classifier: License :: OSI Approved :: MIT License
Classifier: Operating System :: OS Independent
Requires-Python: >=3.6
License-File: LICENSE
Requires-Dist: pandas
